devaria/__init__.py
devaria/cli.py
devaria/client.py
devaria/config.py
devaria/runner.py
devaria/jobs/__init__.py
devaria/jobs/base.py
devaria/jobs/figpack_nwb_raster_plot.py
devaria/jobs/hello_world.py
devaria-0.1.0.dist-info/licenses/LICENSE
devaria-0.1.0.dist-info/METADATA
devaria-0.1.0.dist-info/WHEEL
devaria-0.1.0.dist-info/entry_points.txt
devaria-0.1.0.dist-info/top_level.txt
devaria-0.1.0.dist-info/RECORD
