Metadata-Version: 2.4
Name: devaria
Version: 0.1.0
Summary: Distributed job computation runner for the Devaria system
License: Apache-2.0
Project-URL: Homepage, https://github.com/magland/devaria
Project-URL: Documentation, https://github.com/magland/devaria
Project-URL: Repository, https://github.com/magland/devaria
Keywords: distributed computing,job queue,worker
Classifier: Development Status :: 3 - Alpha
Classifier: Intended Audience :: Developers
Classifier: License :: OSI Approved :: Apache Software License
Classifier: Programming Language :: Python :: 3
Classifier: Programming Language :: Python :: 3.8
Classifier: Programming Language :: Python :: 3.9
Classifier: Programming Language :: Python :: 3.10
Classifier: Programming Language :: Python :: 3.11
Classifier: Programming Language :: Python :: 3.12
Requires-Python: >=3.8
License-File: LICENSE
Requires-Dist: click>=8.1.0
Requires-Dist: requests>=2.31.0
Dynamic: license-file
